simple_pytree/__init__.py
simple_pytree/dataclass.py
simple_pytree/pytree.py
simple_pytree-0.2.2.dist-info/LICENSE
simple_pytree-0.2.2.dist-info/METADATA
simple_pytree-0.2.2.dist-info/WHEEL
simple_pytree-0.2.2.dist-info/RECORD
