Metadata-Version: 2.1
Name: simple-pytree
Version: 0.2.2
Summary: 
License: MIT
Author: Cristian Garcia
Author-email: cgarcia.e88@gmail.com
Requires-Python: >=3.8,<3.12
Classifier: License :: OSI Approved :: MIT License
Classifier: Programming Language :: Python :: 3
Classifier: Programming Language :: Python :: 3.8
Classifier: Programming Language :: Python :: 3.9
Classifier: Programming Language :: Python :: 3.10
Classifier: Programming Language :: Python :: 3.11
Requires-Dist: jax
Requires-Dist: jaxlib
Requires-Dist: typing-extensions
